<annotation>
	<folder>Images</folder>
	<filename>cat.43.jpg</filename>
	<path>P:\Cat_Images_Train\Images\cat.43.jpg</path>
	<source>
		<database>Unknown</database>
	</source>
	<size>
		<width>356</width>
		<height>500</height>
		<depth>3</depth>
	</size>
	<segmented>0</segmented>
	<object>
		<name>cat_face</name>
		<pose>Unspecified</pose>
		<truncated>0</truncated>
		<difficult>0</difficult>
		<bndbox>
			<xmin>139</xmin>
			<ymin>209</ymin>
			<xmax>238</xmax>
			<ymax>303</ymax>
		</bndbox>
	</object>
	<object>
		<name>cat_eyes</name>
		<pose>Unspecified</pose>
		<truncated>0</truncated>
		<difficult>0</difficult>
		<bndbox>
			<xmin>157</xmin>
			<ymin>243</ymin>
			<xmax>177</xmax>
			<ymax>258</ymax>
		</bndbox>
	</object>
	<object>
		<name>cat_eyes</name>
		<pose>Unspecified</pose>
		<truncated>0</truncated>
		<difficult>0</difficult>
		<bndbox>
			<xmin>195</xmin>
			<ymin>248</ymin>
			<xmax>211</xmax>
			<ymax>263</ymax>
		</bndbox>
	</object>
</annotation>
